[
    [
        101,
        "The Lion, the Witch and the Wardrobe",
        1,
        "CSL001",
        "Fantasy",
        "English",
        1950,
        15.99,
        "Fantasy novel for children",
        { "chapters": 17, "pages": 208 }
    ],
    [
        102,
        "The Lord of the Rings",
        2,
        "JRT001",
        "Fantasy",
        "English",
        1954,
        29.99,
        "Epic fantasy trilogy",
        { "books": 3, "pages": 1216 }
    ],
    [
        103,
        "Orthodoxy",
        3,
        "GKC001",
        "Philosophy",
        "English",
        1908,
        12.99,
        "Christian apologetics",
        { "chapters": 9, "pages": 160 }
    ]
]
